{
  "type": "Program",
  "start": 0,
  "end": 552,
  "loc": {
    "start": {
      "line": 1,
      "column": 0
    },
    "end": {
      "line": 37,
      "column": 0
    }
  },
  "sourceType": "module",
  "body": [
    {
      "type": "ImportDeclaration",
      "start": 24,
      "end": 67,
      "loc": {
        "start": {
          "line": 5,
          "column": 0
        },
        "end": {
          "line": 7,
          "column": 15
        }
      },
      "specifiers": [
        {
          "type": "ImportDefaultSpecifier",
          "start": 31,
          "end": 36,
          "loc": {
            "start": {
              "line": 5,
              "column": 7
            },
            "end": {
              "line": 5,
              "column": 12
            }
          },
          "local": {
            "type": "Identifier",
            "start": 31,
            "end": 36,
            "loc": {
              "start": {
                "line": 5,
                "column": 7
              },
              "end": {
                "line": 5,
                "column": 12
              }
            },
            "name": "React",
            "leadingComments": null
          },
          "leadingComments": null
        },
        {
          "type": "ImportSpecifier",
          "start": 42,
          "end": 51,
          "loc": {
            "start": {
              "line": 6,
              "column": 2
            },
            "end": {
              "line": 6,
              "column": 11
            }
          },
          "imported": {
            "type": "Identifier",
            "start": 42,
            "end": 51,
            "loc": {
              "start": {
                "line": 6,
                "column": 2
              },
              "end": {
                "line": 6,
                "column": 11
              }
            },
            "name": "PropTypes"
          },
          "local": {
            "type": "Identifier",
            "start": 42,
            "end": 51,
            "loc": {
              "start": {
                "line": 6,
                "column": 2
              },
              "end": {
                "line": 6,
                "column": 11
              }
            },
            "name": "PropTypes"
          }
        }
      ],
      "importKind": "value",
      "source": {
        "type": "Literal",
        "start": 59,
        "end": 66,
        "loc": {
          "start": {
            "line": 7,
            "column": 7
          },
          "end": {
            "line": 7,
            "column": 14
          }
        },
        "value": "react",
        "rawValue": "react",
        "raw": "'react'"
      },
      "leadingComments": [
        {
          "type": "Block",
          "value": "*\n * @author haw\n ",
          "start": 0,
          "end": 22,
          "loc": {
            "start": {
              "line": 1,
              "column": 0
            },
            "end": {
              "line": 3,
              "column": 3
            }
          },
          "range": [
            0,
            22
          ]
        }
      ]
    },
    {
      "type": "ImportDeclaration",
      "start": 68,
      "end": 103,
      "loc": {
        "start": {
          "line": 8,
          "column": 0
        },
        "end": {
          "line": 8,
          "column": 35
        }
      },
      "specifiers": [
        {
          "type": "ImportSpecifier",
          "start": 76,
          "end": 86,
          "loc": {
            "start": {
              "line": 8,
              "column": 8
            },
            "end": {
              "line": 8,
              "column": 18
            }
          },
          "imported": {
            "type": "Identifier",
            "start": 76,
            "end": 86,
            "loc": {
              "start": {
                "line": 8,
                "column": 8
              },
              "end": {
                "line": 8,
                "column": 18
              }
            },
            "name": "classNames"
          },
          "local": {
            "type": "Identifier",
            "start": 76,
            "end": 86,
            "loc": {
              "start": {
                "line": 8,
                "column": 8
              },
              "end": {
                "line": 8,
                "column": 18
              }
            },
            "name": "classNames"
          }
        }
      ],
      "importKind": "value",
      "source": {
        "type": "Literal",
        "start": 93,
        "end": 102,
        "loc": {
          "start": {
            "line": 8,
            "column": 25
          },
          "end": {
            "line": 8,
            "column": 34
          }
        },
        "value": "../util",
        "rawValue": "../util",
        "raw": "'../util'"
      }
    },
    {
      "type": "VariableDeclaration",
      "start": 105,
      "end": 135,
      "loc": {
        "start": {
          "line": 10,
          "column": 0
        },
        "end": {
          "line": 10,
          "column": 30
        }
      },
      "declarations": [
        {
          "type": "VariableDeclarator",
          "start": 111,
          "end": 134,
          "loc": {
            "start": {
              "line": 10,
              "column": 6
            },
            "end": {
              "line": 10,
              "column": 29
            }
          },
          "id": {
            "type": "Identifier",
            "start": 111,
            "end": 117,
            "loc": {
              "start": {
                "line": 10,
                "column": 6
              },
              "end": {
                "line": 10,
                "column": 12
              }
            },
            "name": "prefix"
          },
          "init": {
            "type": "Literal",
            "start": 120,
            "end": 134,
            "loc": {
              "start": {
                "line": 10,
                "column": 15
              },
              "end": {
                "line": 10,
                "column": 29
              }
            },
            "value": "alert-header",
            "rawValue": "alert-header",
            "raw": "'alert-header'"
          }
        }
      ],
      "kind": "const",
      "trailingComments": [
        {
          "type": "Block",
          "value": "*\n * AlertHeader 警告框头部组件\n * @param {Object} props 组件所使用的属性\n ",
          "start": 137,
          "end": 201,
          "loc": {
            "start": {
              "line": 12,
              "column": 0
            },
            "end": {
              "line": 15,
              "column": 3
            }
          },
          "range": [
            137,
            201
          ]
        }
      ]
    },
    {
      "type": "ExportDefaultDeclaration",
      "start": 202,
      "end": 463,
      "loc": {
        "start": {
          "line": 16,
          "column": 0
        },
        "end": {
          "line": 31,
          "column": 1
        }
      },
      "declaration": {
        "type": "FunctionDeclaration",
        "start": 217,
        "end": 463,
        "loc": {
          "start": {
            "line": 16,
            "column": 15
          },
          "end": {
            "line": 31,
            "column": 1
          }
        },
        "id": {
          "type": "Identifier",
          "start": 226,
          "end": 237,
          "loc": {
            "start": {
              "line": 16,
              "column": 24
            },
            "end": {
              "line": 16,
              "column": 35
            }
          },
          "name": "AlertHeader",
          "leadingComments": null
        },
        "generator": false,
        "expression": false,
        "async": false,
        "params": [
          {
            "type": "Identifier",
            "start": 238,
            "end": 243,
            "loc": {
              "start": {
                "line": 16,
                "column": 36
              },
              "end": {
                "line": 16,
                "column": 41
              }
            },
            "name": "props"
          }
        ],
        "body": {
          "type": "BlockStatement",
          "start": 245,
          "end": 463,
          "loc": {
            "start": {
              "line": 16,
              "column": 43
            },
            "end": {
              "line": 31,
              "column": 1
            }
          },
          "body": [
            {
              "type": "VariableDeclaration",
              "start": 249,
              "end": 310,
              "loc": {
                "start": {
                  "line": 17,
                  "column": 2
                },
                "end": {
                  "line": 21,
                  "column": 12
                }
              },
              "declarations": [
                {
                  "type": "VariableDeclarator",
                  "start": 255,
                  "end": 309,
                  "loc": {
                    "start": {
                      "line": 17,
                      "column": 8
                    },
                    "end": {
                      "line": 21,
                      "column": 11
                    }
                  },
                  "id": {
                    "type": "ObjectPattern",
                    "start": 255,
                    "end": 301,
                    "loc": {
                      "start": {
                        "line": 17,
                        "column": 8
                      },
                      "end": {
                        "line": 21,
                        "column": 3
                      }
                    },
                    "properties": [
                      {
                        "type": "Property",
                        "start": 261,
                        "end": 270,
                        "loc": {
                          "start": {
                            "line": 18,
                            "column": 4
                          },
                          "end": {
                            "line": 18,
                            "column": 13
                          }
                        },
                        "method": false,
                        "shorthand": true,
                        "computed": false,
                        "key": {
                          "type": "Identifier",
                          "start": 261,
                          "end": 270,
                          "loc": {
                            "start": {
                              "line": 18,
                              "column": 4
                            },
                            "end": {
                              "line": 18,
                              "column": 13
                            }
                          },
                          "name": "className"
                        },
                        "kind": "init",
                        "value": {
                          "type": "Identifier",
                          "start": 261,
                          "end": 270,
                          "loc": {
                            "start": {
                              "line": 18,
                              "column": 4
                            },
                            "end": {
                              "line": 18,
                              "column": 13
                            }
                          },
                          "name": "className"
                        }
                      },
                      {
                        "type": "Property",
                        "start": 276,
                        "end": 284,
                        "loc": {
                          "start": {
                            "line": 19,
                            "column": 4
                          },
                          "end": {
                            "line": 19,
                            "column": 12
                          }
                        },
                        "method": false,
                        "shorthand": true,
                        "computed": false,
                        "key": {
                          "type": "Identifier",
                          "start": 276,
                          "end": 284,
                          "loc": {
                            "start": {
                              "line": 19,
                              "column": 4
                            },
                            "end": {
                              "line": 19,
                              "column": 12
                            }
                          },
                          "name": "children"
                        },
                        "kind": "init",
                        "value": {
                          "type": "Identifier",
                          "start": 276,
                          "end": 284,
                          "loc": {
                            "start": {
                              "line": 19,
                              "column": 4
                            },
                            "end": {
                              "line": 19,
                              "column": 12
                            }
                          },
                          "name": "children"
                        }
                      },
                      {
                        "type": "SpreadProperty",
                        "start": 290,
                        "end": 297,
                        "loc": {
                          "start": {
                            "line": 20,
                            "column": 4
                          },
                          "end": {
                            "line": 20,
                            "column": 11
                          }
                        },
                        "argument": {
                          "type": "Identifier",
                          "start": 293,
                          "end": 297,
                          "loc": {
                            "start": {
                              "line": 20,
                              "column": 7
                            },
                            "end": {
                              "line": 20,
                              "column": 11
                            }
                          },
                          "name": "rest"
                        }
                      }
                    ]
                  },
                  "init": {
                    "type": "Identifier",
                    "start": 304,
                    "end": 309,
                    "loc": {
                      "start": {
                        "line": 21,
                        "column": 6
                      },
                      "end": {
                        "line": 21,
                        "column": 11
                      }
                    },
                    "name": "props"
                  }
                }
              ],
              "kind": "const"
            },
            {
              "type": "VariableDeclaration",
              "start": 313,
              "end": 378,
              "loc": {
                "start": {
                  "line": 22,
                  "column": 2
                },
                "end": {
                  "line": 24,
                  "column": 5
                }
              },
              "declarations": [
                {
                  "type": "VariableDeclarator",
                  "start": 317,
                  "end": 377,
                  "loc": {
                    "start": {
                      "line": 22,
                      "column": 6
                    },
                    "end": {
                      "line": 24,
                      "column": 4
                    }
                  },
                  "id": {
                    "type": "Identifier",
                    "start": 317,
                    "end": 322,
                    "loc": {
                      "start": {
                        "line": 22,
                        "column": 6
                      },
                      "end": {
                        "line": 22,
                        "column": 11
                      }
                    },
                    "name": "clazz"
                  },
                  "init": {
                    "type": "CallExpression",
                    "start": 325,
                    "end": 377,
                    "loc": {
                      "start": {
                        "line": 22,
                        "column": 14
                      },
                      "end": {
                        "line": 24,
                        "column": 4
                      }
                    },
                    "callee": {
                      "type": "Identifier",
                      "start": 325,
                      "end": 335,
                      "loc": {
                        "start": {
                          "line": 22,
                          "column": 14
                        },
                        "end": {
                          "line": 22,
                          "column": 24
                        }
                      },
                      "name": "classNames"
                    },
                    "arguments": [
                      {
                        "type": "Identifier",
                        "start": 336,
                        "end": 342,
                        "loc": {
                          "start": {
                            "line": 22,
                            "column": 25
                          },
                          "end": {
                            "line": 22,
                            "column": 31
                          }
                        },
                        "name": "prefix"
                      },
                      {
                        "type": "ObjectExpression",
                        "start": 344,
                        "end": 376,
                        "loc": {
                          "start": {
                            "line": 22,
                            "column": 33
                          },
                          "end": {
                            "line": 24,
                            "column": 3
                          }
                        },
                        "properties": [
                          {
                            "type": "Property",
                            "start": 350,
                            "end": 372,
                            "loc": {
                              "start": {
                                "line": 23,
                                "column": 4
                              },
                              "end": {
                                "line": 23,
                                "column": 26
                              }
                            },
                            "method": false,
                            "shorthand": false,
                            "computed": true,
                            "key": {
                              "type": "Identifier",
                              "start": 351,
                              "end": 360,
                              "loc": {
                                "start": {
                                  "line": 23,
                                  "column": 5
                                },
                                "end": {
                                  "line": 23,
                                  "column": 14
                                }
                              },
                              "name": "className"
                            },
                            "value": {
                              "type": "Identifier",
                              "start": 363,
                              "end": 372,
                              "loc": {
                                "start": {
                                  "line": 23,
                                  "column": 17
                                },
                                "end": {
                                  "line": 23,
                                  "column": 26
                                }
                              },
                              "name": "className"
                            },
                            "kind": "init"
                          }
                        ]
                      }
                    ]
                  }
                }
              ],
              "kind": "let"
            },
            {
              "type": "ReturnStatement",
              "start": 382,
              "end": 461,
              "loc": {
                "start": {
                  "line": 26,
                  "column": 2
                },
                "end": {
                  "line": 30,
                  "column": 4
                }
              },
              "argument": {
                "type": "JSXElement",
                "start": 395,
                "end": 456,
                "loc": {
                  "start": {
                    "line": 27,
                    "column": 4
                  },
                  "end": {
                    "line": 29,
                    "column": 10
                  }
                },
                "openingElement": {
                  "type": "JSXOpeningElement",
                  "start": 395,
                  "end": 428,
                  "loc": {
                    "start": {
                      "line": 27,
                      "column": 4
                    },
                    "end": {
                      "line": 27,
                      "column": 37
                    }
                  },
                  "attributes": [
                    {
                      "type": "JSXAttribute",
                      "start": 400,
                      "end": 417,
                      "loc": {
                        "start": {
                          "line": 27,
                          "column": 9
                        },
                        "end": {
                          "line": 27,
                          "column": 26
                        }
                      },
                      "name": {
                        "type": "JSXIdentifier",
                        "start": 400,
                        "end": 409,
                        "loc": {
                          "start": {
                            "line": 27,
                            "column": 9
                          },
                          "end": {
                            "line": 27,
                            "column": 18
                          }
                        },
                        "name": "className"
                      },
                      "value": {
                        "type": "JSXExpressionContainer",
                        "start": 410,
                        "end": 417,
                        "loc": {
                          "start": {
                            "line": 27,
                            "column": 19
                          },
                          "end": {
                            "line": 27,
                            "column": 26
                          }
                        },
                        "expression": {
                          "type": "Identifier",
                          "start": 411,
                          "end": 416,
                          "loc": {
                            "start": {
                              "line": 27,
                              "column": 20
                            },
                            "end": {
                              "line": 27,
                              "column": 25
                            }
                          },
                          "name": "clazz"
                        }
                      }
                    },
                    {
                      "type": "JSXSpreadAttribute",
                      "start": 418,
                      "end": 427,
                      "loc": {
                        "start": {
                          "line": 27,
                          "column": 27
                        },
                        "end": {
                          "line": 27,
                          "column": 36
                        }
                      },
                      "argument": {
                        "type": "Identifier",
                        "start": 422,
                        "end": 426,
                        "loc": {
                          "start": {
                            "line": 27,
                            "column": 31
                          },
                          "end": {
                            "line": 27,
                            "column": 35
                          }
                        },
                        "name": "rest"
                      }
                    }
                  ],
                  "name": {
                    "type": "JSXIdentifier",
                    "start": 396,
                    "end": 399,
                    "loc": {
                      "start": {
                        "line": 27,
                        "column": 5
                      },
                      "end": {
                        "line": 27,
                        "column": 8
                      }
                    },
                    "name": "div"
                  },
                  "selfClosing": false
                },
                "closingElement": {
                  "type": "JSXClosingElement",
                  "start": 450,
                  "end": 456,
                  "loc": {
                    "start": {
                      "line": 29,
                      "column": 4
                    },
                    "end": {
                      "line": 29,
                      "column": 10
                    }
                  },
                  "name": {
                    "type": "JSXIdentifier",
                    "start": 452,
                    "end": 455,
                    "loc": {
                      "start": {
                        "line": 29,
                        "column": 6
                      },
                      "end": {
                        "line": 29,
                        "column": 9
                      }
                    },
                    "name": "div"
                  }
                },
                "children": [
                  {
                    "type": "Literal",
                    "start": 428,
                    "end": 435,
                    "loc": {
                      "start": {
                        "line": 27,
                        "column": 37
                      },
                      "end": {
                        "line": 28,
                        "column": 6
                      }
                    },
                    "value": "\n      ",
                    "rawValue": null,
                    "raw": "\n      "
                  },
                  {
                    "type": "JSXExpressionContainer",
                    "start": 435,
                    "end": 445,
                    "loc": {
                      "start": {
                        "line": 28,
                        "column": 6
                      },
                      "end": {
                        "line": 28,
                        "column": 16
                      }
                    },
                    "expression": {
                      "type": "Identifier",
                      "start": 436,
                      "end": 444,
                      "loc": {
                        "start": {
                          "line": 28,
                          "column": 7
                        },
                        "end": {
                          "line": 28,
                          "column": 15
                        }
                      },
                      "name": "children"
                    }
                  },
                  {
                    "type": "Literal",
                    "start": 445,
                    "end": 450,
                    "loc": {
                      "start": {
                        "line": 28,
                        "column": 16
                      },
                      "end": {
                        "line": 29,
                        "column": 4
                      }
                    },
                    "value": "\n    ",
                    "rawValue": null,
                    "raw": "\n    "
                  }
                ],
                "parenthesizedExpression": true
              }
            }
          ]
        },
        "leadingComments": [
          {
            "type": "Block",
            "value": "*\n * AlertHeader 警告框头部组件\n * @param {Object} props 组件所使用的属性\n ",
            "start": 137,
            "end": 201,
            "loc": {
              "start": {
                "line": 12,
                "column": 0
              },
              "end": {
                "line": 15,
                "column": 3
              }
            },
            "range": [
              137,
              201
            ]
          }
        ],
        "trailingComments": []
      },
      "leadingComments": [
        {
          "type": "Block",
          "value": "*\n * AlertHeader 警告框头部组件\n * @param {Object} props 组件所使用的属性\n ",
          "start": 137,
          "end": 201,
          "loc": {
            "start": {
              "line": 12,
              "column": 0
            },
            "end": {
              "line": 15,
              "column": 3
            }
          },
          "range": [
            137,
            201
          ]
        }
      ]
    },
    {
      "type": "ExpressionStatement",
      "start": 465,
      "end": 551,
      "loc": {
        "start": {
          "line": 33,
          "column": 0
        },
        "end": {
          "line": 36,
          "column": 2
        }
      },
      "expression": {
        "type": "AssignmentExpression",
        "start": 465,
        "end": 550,
        "loc": {
          "start": {
            "line": 33,
            "column": 0
          },
          "end": {
            "line": 36,
            "column": 1
          }
        },
        "operator": "=",
        "left": {
          "type": "MemberExpression",
          "start": 465,
          "end": 486,
          "loc": {
            "start": {
              "line": 33,
              "column": 0
            },
            "end": {
              "line": 33,
              "column": 21
            }
          },
          "object": {
            "type": "Identifier",
            "start": 465,
            "end": 476,
            "loc": {
              "start": {
                "line": 33,
                "column": 0
              },
              "end": {
                "line": 33,
                "column": 11
              }
            },
            "name": "AlertHeader"
          },
          "property": {
            "type": "Identifier",
            "start": 477,
            "end": 486,
            "loc": {
              "start": {
                "line": 33,
                "column": 12
              },
              "end": {
                "line": 33,
                "column": 21
              }
            },
            "name": "propTypes"
          },
          "computed": false
        },
        "right": {
          "type": "ObjectExpression",
          "start": 489,
          "end": 550,
          "loc": {
            "start": {
              "line": 33,
              "column": 24
            },
            "end": {
              "line": 36,
              "column": 1
            }
          },
          "properties": [
            {
              "type": "Property",
              "start": 493,
              "end": 520,
              "loc": {
                "start": {
                  "line": 34,
                  "column": 2
                },
                "end": {
                  "line": 34,
                  "column": 29
                }
              },
              "method": false,
              "shorthand": false,
              "computed": false,
              "key": {
                "type": "Identifier",
                "start": 493,
                "end": 502,
                "loc": {
                  "start": {
                    "line": 34,
                    "column": 2
                  },
                  "end": {
                    "line": 34,
                    "column": 11
                  }
                },
                "name": "className"
              },
              "value": {
                "type": "MemberExpression",
                "start": 504,
                "end": 520,
                "loc": {
                  "start": {
                    "line": 34,
                    "column": 13
                  },
                  "end": {
                    "line": 34,
                    "column": 29
                  }
                },
                "object": {
                  "type": "Identifier",
                  "start": 504,
                  "end": 513,
                  "loc": {
                    "start": {
                      "line": 34,
                      "column": 13
                    },
                    "end": {
                      "line": 34,
                      "column": 22
                    }
                  },
                  "name": "PropTypes"
                },
                "property": {
                  "type": "Identifier",
                  "start": 514,
                  "end": 520,
                  "loc": {
                    "start": {
                      "line": 34,
                      "column": 23
                    },
                    "end": {
                      "line": 34,
                      "column": 29
                    }
                  },
                  "name": "string"
                },
                "computed": false
              },
              "kind": "init"
            },
            {
              "type": "Property",
              "start": 524,
              "end": 548,
              "loc": {
                "start": {
                  "line": 35,
                  "column": 2
                },
                "end": {
                  "line": 35,
                  "column": 26
                }
              },
              "method": false,
              "shorthand": false,
              "computed": false,
              "key": {
                "type": "Identifier",
                "start": 524,
                "end": 532,
                "loc": {
                  "start": {
                    "line": 35,
                    "column": 2
                  },
                  "end": {
                    "line": 35,
                    "column": 10
                  }
                },
                "name": "children"
              },
              "value": {
                "type": "MemberExpression",
                "start": 534,
                "end": 548,
                "loc": {
                  "start": {
                    "line": 35,
                    "column": 12
                  },
                  "end": {
                    "line": 35,
                    "column": 26
                  }
                },
                "object": {
                  "type": "Identifier",
                  "start": 534,
                  "end": 543,
                  "loc": {
                    "start": {
                      "line": 35,
                      "column": 12
                    },
                    "end": {
                      "line": 35,
                      "column": 21
                    }
                  },
                  "name": "PropTypes"
                },
                "property": {
                  "type": "Identifier",
                  "start": 544,
                  "end": 548,
                  "loc": {
                    "start": {
                      "line": 35,
                      "column": 22
                    },
                    "end": {
                      "line": 35,
                      "column": 26
                    }
                  },
                  "name": "node"
                },
                "computed": false
              },
              "kind": "init"
            }
          ]
        }
      }
    }
  ]
}